clean_workspace/__init__.py
clean_workspace/archive.py
clean_workspace/blacklist_domains.txt
clean_workspace/blacklist_urls.txt
clean_workspace/internet.py
clean_workspace/patch.py
clean_workspace/utils.py
clean_workspace-0.8.2.dist-info/LICENSE
clean_workspace-0.8.2.dist-info/METADATA
clean_workspace-0.8.2.dist-info/WHEEL
clean_workspace-0.8.2.dist-info/entry_points.txt
clean_workspace-0.8.2.dist-info/RECORD
