Metadata-Version: 2.1
Name: clean-workspace
Version: 0.8.2
Summary: Collect all browser URLs, output to terminal, and archive to todoist. Useful for cleaning up your workspace at the end of the day, without loosing important urls.
Home-page: https://github.com/iloveitaly/clean-browser
License: MIT
Keywords: todoist,browser,productivity
Author: Mike Bianco
Author-email: mike@mikebian.co
Requires-Python: >=3.10,<4.0
Classifier: License :: OSI Approved :: MIT License
Classifier: Programming Language :: Python :: 3
Classifier: Programming Language :: Python :: 3.10
Classifier: Programming Language :: Python :: 3.11
Classifier: Programming Language :: Python :: 3.12
Requires-Dist: backoff (>=2.2.1,<3.0.0)
Requires-Dist: chrome-bookmarks (>=2020.10.25,<2021.0.0)
Requires-Dist: click (>=8.1.7,<9.0.0)
Requires-Dist: pyobjc-framework-ScriptingBridge (>=10.3.1,<11.0.0)
Requires-Dist: todoist-api-python (==2.1.7)
